aionvk/__init__.py
aionvk/bot/__init__.py
aionvk/bot/bot.py
aionvk/bot/callback_data.py
aionvk/bot/dispatcher.py
aionvk/bot/filters.py
aionvk/bot/fsm/__init__.py
aionvk/bot/fsm/context.py
aionvk/bot/fsm/middleware.py
aionvk/bot/fsm/redis.py
aionvk/bot/fsm/state.py
aionvk/bot/fsm/storage.py
aionvk/bot/handlers.py
aionvk/bot/middleware.py
aionvk/bot/router.py
aionvk/builders/__init__.py
aionvk/builders/keyboard.py
aionvk/builders/paginator.py
aionvk/client.py
aionvk/exceptions.py
aionvk/magic.py
aionvk/types.py
aionvk/utils/__init__.py
aionvk/utils/text.py
aionvk-0.4.13.dist-info/METADATA
aionvk-0.4.13.dist-info/WHEEL
aionvk-0.4.13.dist-info/RECORD
